git_root_to_syspath/__init__.py
git_root_to_syspath/git_root_to_syspath.py
git_root_to_syspath-0.1.dist-info/LICENSE
git_root_to_syspath-0.1.dist-info/METADATA
git_root_to_syspath-0.1.dist-info/WHEEL
git_root_to_syspath-0.1.dist-info/top_level.txt
git_root_to_syspath-0.1.dist-info/RECORD
