Metadata-Version: 2.1
Name: git_root_to_syspath
Version: 0.1
Summary: Inserts the nearest git repository root into sys.path.
Home-page: https://gitlab.com/ivo-marvan/git_root_to_syspath
Author: Ivo Marvan
Author-email: ivo@marvan.cz
Classifier: Programming Language :: Python :: 3
Classifier: License :: OSI Approved :: MIT License
Classifier: Operating System :: OS Independent
License-File: LICENSE
